alibabacloud_selectdb20230522/__init__.py
alibabacloud_selectdb20230522/client.py
alibabacloud_selectdb20230522/models/__init__.py
alibabacloud_selectdb20230522/models/_allocate_instance_public_connection_request.py
alibabacloud_selectdb20230522/models/_allocate_instance_public_connection_response.py
alibabacloud_selectdb20230522/models/_allocate_instance_public_connection_response_body.py
alibabacloud_selectdb20230522/models/_change_resource_group_request.py
alibabacloud_selectdb20230522/models/_change_resource_group_response.py
alibabacloud_selectdb20230522/models/_change_resource_group_response_body.py
alibabacloud_selectdb20230522/models/_check_create_dbinstance_request.py
alibabacloud_selectdb20230522/models/_check_create_dbinstance_response.py
alibabacloud_selectdb20230522/models/_check_create_dbinstance_response_body.py
alibabacloud_selectdb20230522/models/_check_ip_exists_in_security_ip_list_request.py
alibabacloud_selectdb20230522/models/_check_ip_exists_in_security_ip_list_response.py
alibabacloud_selectdb20230522/models/_check_ip_exists_in_security_ip_list_response_body.py
alibabacloud_selectdb20230522/models/_check_service_linked_role_request.py
alibabacloud_selectdb20230522/models/_check_service_linked_role_response.py
alibabacloud_selectdb20230522/models/_check_service_linked_role_response_body.py
alibabacloud_selectdb20230522/models/_create_dbcluster_binding_request.py
alibabacloud_selectdb20230522/models/_create_dbcluster_binding_response.py
alibabacloud_selectdb20230522/models/_create_dbcluster_binding_response_body.py
alibabacloud_selectdb20230522/models/_create_dbcluster_request.py
alibabacloud_selectdb20230522/models/_create_dbcluster_response.py
alibabacloud_selectdb20230522/models/_create_dbcluster_response_body.py
alibabacloud_selectdb20230522/models/_create_dbinstance_request.py
alibabacloud_selectdb20230522/models/_create_dbinstance_response.py
alibabacloud_selectdb20230522/models/_create_dbinstance_response_body.py
alibabacloud_selectdb20230522-5.0.2.dist-info/LICENSE
alibabacloud_selectdb20230522-5.0.2.dist-info/METADATA
alibabacloud_selectdb20230522-5.0.2.dist-info/WHEEL
alibabacloud_selectdb20230522-5.0.2.dist-info/top_level.txt
alibabacloud_selectdb20230522-5.0.2.dist-info/RECORD
